codefest/cf04_deliverable/codefest/cf04/hdl/mac_correct.v
// mac_correct.v
// Corrected 8-bit signed multiply-accumulate unit
// - Signed operands and accumulator
// - Synchronous active-high reset
// - always_ff for sequential logic
// - Explicit sign extension of the 16-bit product to 32 bits

module mac (
    input  logic               clk,
    input  logic               rst,
    input  logic signed [7:0]  a,
    input  logic signed [7:0]  b,
    output logic signed [31:0] out
);

    logic signed [15:0] product;
    logic signed [31:0] product_ext;

    // Combinational multiply, then explicit sign extension to 32 bits
    assign product     = a * b;
    assign product_ext = {{16{product[15]}}, product};

    always_ff @(posedge clk) begin
        if (rst)
            out <= 32'sd0;
        else
            out <= out + product_ext;
    end

endmodule

codefest/cf04_deliverable/codefest/cf04/hdl/mac_tb.v
// mac_tb.v
// Testbench for the mac module
// Stimulus per CF04 spec:
//   [a=3, b=4]  for 3 cycles
//   assert rst
//   [a=-5, b=2] for 2 cycles

`timescale 1ns/1ps

module mac_tb;

    logic               clk;
    logic               rst;
    logic signed [7:0]  a;
    logic signed [7:0]  b;
    logic signed [31:0] out;

    // DUT
    mac dut (
        .clk(clk),
        .rst(rst),
        .a(a),
        .b(b),
        .out(out)
    );

    // 100 MHz clock
    initial clk = 0;
    always #5 clk = ~clk;

    // VCD dump for GTKWave
    initial begin
        $dumpfile("dump.vcd");
        $dumpvars(0, mac_tb);
    end

    initial begin
        // Init + initial reset
        rst = 1;
        a   = 8'sd0;
        b   = 8'sd0;
        @(posedge clk); #1;
        rst = 0;
        $display("after reset    : out = %0d (expect 0)", out);

        // Phase 1: a=3, b=4 for 3 cycles -> 12, 24, 36
        a = 8'sd3;
        b = 8'sd4;
        @(posedge clk); #1;
        $display("cycle 1 (3*4)  : out = %0d (expect 12)", out);
        @(posedge clk); #1;
        $display("cycle 2 (3*4)  : out = %0d (expect 24)", out);
        @(posedge clk); #1;
        $display("cycle 3 (3*4)  : out = %0d (expect 36)", out);

        // Assert rst
        rst = 1;
        @(posedge clk); #1;
        $display("after rst pulse: out = %0d (expect 0)", out);
        rst = 0;

        // Phase 2: a=-5, b=2 for 2 cycles -> -10, -20
        a = -8'sd5;
        b =  8'sd2;
        @(posedge clk); #1;
        $display("cycle 4 (-5*2) : out = %0d (expect -10)", out);
        @(posedge clk); #1;
        $display("cycle 5 (-5*2) : out = %0d (expect -20)", out);

        // Pass/fail summary
        if (out === -32'sd20)
            $display("RESULT: PASS");
        else
            $display("RESULT: FAIL  (final out = %0d, expected -20)", out);

        $finish;
    end

endmodule

codefest/cf04/cocotb_mac/dump.vcd
$date
	Mon Apr 27 01:40:25 2026
$end
$version
	Icarus Verilog
$end
$timescale
	1ps
$end
$scope module mac_tb $end
$var wire 32 ! out [31:0] $end
$var reg 8 " a [7:0] $end
$var reg 8 # b [7:0] $end
$var reg 1 $ clk $end
$var reg 1 % rst $end
$scope module dut $end
$var wire 8 & a [7:0] $end
$var wire 8 ' b [7:0] $end
$var wire 1 $ clk $end
$var wire 1 % rst $end
$var wire 32 ( product_ext [31:0] $end
$var wire 16 ) product [15:0] $end
$var reg 32 * out [31:0] $end
$upscope $end
$upscope $end
$enddefinitions $end
$comment Show the parameter values. $end
$dumpall
$end
#0
$dumpvars
bx *
b0 )
b0 (
b0 '
b0 &
1%
0$
b0 #
b0 "
bx !
$end
#5000
b0 !
b0 *
1$
#6000
b1100 (
b1100 )
b100 #
b100 '
b11 "
b11 &
0%
#10000
0$
#15000
b1100 !
b1100 *
1$
#20000
0$
#25000
b11000 !
b11000 *
1$
#30000
0$
#35000
b100100 !
b100100 *
1$
#36000
1%
#40000
0$
#45000
b0 !
b0 *
1$
#46000
b10 #
b10 '
b11111111111111111111111111110110 (
b1111111111110110 )
b11111011 "
b11111011 &
0%
#50000
0$
#55000
b11111111111111111111111111110110 !
b11111111111111111111111111110110 *
1$
#60000
0$
#65000
b11111111111111111111111111101100 !
b11111111111111111111111111101100 *
1$
